odoo/addons/website_rma/README.rst
odoo/addons/website_rma/__init__.py
odoo/addons/website_rma/__manifest__.py
odoo/addons/website_rma/controllers/__init__.py
odoo/addons/website_rma/controllers/main.py
odoo/addons/website_rma/data/ir_model_data.xml
odoo/addons/website_rma/data/website_data.xml
odoo/addons/website_rma/i18n/es.po
odoo/addons/website_rma/i18n/pt.po
odoo/addons/website_rma/i18n/pt_BR.po
odoo/addons/website_rma/i18n/website_rma.pot
odoo/addons/website_rma/models/__init__.py
odoo/addons/website_rma/models/ir_model.py
odoo/addons/website_rma/readme/CONTRIBUTORS.rst
odoo/addons/website_rma/readme/DESCRIPTION.rst
odoo/addons/website_rma/readme/USAGE.rst
odoo/addons/website_rma/static/description/icon.png
odoo/addons/website_rma/static/description/index.html
odoo/addons/website_rma/static/src/js/website_rma.js
odoo/addons/website_rma/static/src/js/website_rma.tour.js
odoo/addons/website_rma/tests/__init__.py
odoo/addons/website_rma/tests/test_website_rma.py
odoo/addons/website_rma/views/assets.xml
odoo/addons/website_rma/views/request_rma_form.xml
odoo/addons/website_rma/views/website_rma_portal_templates.xml
odoo/addons/website_rma/views/website_templates.xml
odoo12_addon_website_rma-12.0.1.1.2.dist-info/METADATA
odoo12_addon_website_rma-12.0.1.1.2.dist-info/WHEEL
odoo12_addon_website_rma-12.0.1.1.2.dist-info/top_level.txt
odoo12_addon_website_rma-12.0.1.1.2.dist-info/RECORD
